Workbook

Sheet Tổng hợp
A1: TỔNG HỢP TIẾN ĐỘ UX/UI
A3: Theo nhóm | B3: Số màn hình | C3: Thiết kế | D3: Code UI | E3: Nối API | F3: Test | G3: Hoàn thành | H3: % hoàn thành
A4: A. Công khai & xác thực | B4: =COUNTIF('Trang UXUI'!$B$5:$B$72,A4) | C4: =COUNTIFS('Trang UXUI'!$B$5:$B$72,$A4,'Trang UXUI'!$J$5:$J$72,"☑") | D4: =COUNTIFS('Trang UXUI'!$B$5:$B$72,$A4,'Trang UXUI'!$K$5:$K$72,"☑") | E4: =COUNTIFS('Trang UXUI'!$B$5:$B$72,$A4,'Trang UXUI'!$L$5:$L$72,"☑") | F4: =COUNTIFS('Trang UXUI'!$B$5:$B$72,$A4,'Trang UXUI'!$M$5:$M$72,"☑") | G4: =COUNTIFS('Trang UXUI'!$B$5:$B$72,$A4,'Trang UXUI'!$N$5:$N$72,"✔ Xong") | H4: =IF(B4=0,0,G4/B4)
A5: B. Khung ứng dụng | B5: =COUNTIF('Trang UXUI'!$B$5:$B$72,A5) | C5: =COUNTIFS('Trang UXUI'!$B$5:$B$72,$A5,'Trang UXUI'!$J$5:$J$72,"☑") | D5: =COUNTIFS('Trang UXUI'!$B$5:$B$72,$A5,'Trang UXUI'!$K$5:$K$72,"☑") | E5: =COUNTIFS('Trang UXUI'!$B$5:$B$72,$A5,'Trang UXUI'!$L$5:$L$72,"☑") | F5: =COUNTIFS('Trang UXUI'!$B$5:$B$72,$A5,'Trang UXUI'!$M$5:$M$72,"☑") | G5: =COUNTIFS('Trang UXUI'!$B$5:$B$72,$A5,'Trang UXUI'!$N$5:$N$72,"✔ Xong") | H5: =IF(B5=0,0,G5/B5)
A6: C. Danh mục | B6: =COUNTIF('Trang UXUI'!$B$5:$B$72,A6) | C6: =COUNTIFS('Trang UXUI'!$B$5:$B$72,$A6,'Trang UXUI'!$J$5:$J$72,"☑") | D6: =COUNTIFS('Trang UXUI'!$B$5:$B$72,$A6,'Trang UXUI'!$K$5:$K$72,"☑") | E6: =COUNTIFS('Trang UXUI'!$B$5:$B$72,$A6,'Trang UXUI'!$L$5:$L$72,"☑") | F6: =COUNTIFS('Trang UXUI'!$B$5:$B$72,$A6,'Trang UXUI'!$M$5:$M$72,"☑") | G6: =COUNTIFS('Trang UXUI'!$B$5:$B$72,$A6,'Trang UXUI'!$N$5:$N$72,"✔ Xong") | H6: =IF(B6=0,0,G6/B6)
A7: D. Tồn kho | B7: =COUNTIF('Trang UXUI'!$B$5:$B$72,A7) | C7: =COUNTIFS('Trang UXUI'!$B$5:$B$72,$A7,'Trang UXUI'!$J$5:$J$72,"☑") | D7: =COUNTIFS('Trang UXUI'!$B$5:$B$72,$A7,'Trang UXUI'!$K$5:$K$72,"☑") | E7: =COUNTIFS('Trang UXUI'!$B$5:$B$72,$A7,'Trang UXUI'!$L$5:$L$72,"☑") | F7: =COUNTIFS('Trang UXUI'!$B$5:$B$72,$A7,'Trang UXUI'!$M$5:$M$72,"☑") | G7: =COUNTIFS('Trang UXUI'!$B$5:$B$72,$A7,'Trang UXUI'!$N$5:$N$72,"✔ Xong") | H7: =IF(B7=0,0,G7/B7)
A8: E. Phiếu nhập | B8: =COUNTIF('Trang UXUI'!$B$5:$B$72,A8) | C8: =COUNTIFS('Trang UXUI'!$B$5:$B$72,$A8,'Trang UXUI'!$J$5:$J$72,"☑") | D8: =COUNTIFS('Trang UXUI'!$B$5:$B$72,$A8,'Trang UXUI'!$K$5:$K$72,"☑") | E8: =COUNTIFS('Trang UXUI'!$B$5:$B$72,$A8,'Trang UXUI'!$L$5:$L$72,"☑") | F8: =COUNTIFS('Trang UXUI'!$B$5:$B$72,$A8,'Trang UXUI'!$M$5:$M$72,"☑") | G8: =COUNTIFS('Trang UXUI'!$B$5:$B$72,$A8,'Trang UXUI'!$N$5:$N$72,"✔ Xong") | H8: =IF(B8=0,0,G8/B8)
A9: F. Phiếu xuất | B9: =COUNTIF('Trang UXUI'!$B$5:$B$72,A9) | C9: =COUNTIFS('Trang UXUI'!$B$5:$B$72,$A9,'Trang UXUI'!$J$5:$J$72,"☑") | D9: =COUNTIFS('Trang UXUI'!$B$5:$B$72,$A9,'Trang UXUI'!$K$5:$K$72,"☑") | E9: =COUNTIFS('Trang UXUI'!$B$5:$B$72,$A9,'Trang UXUI'!$L$5:$L$72,"☑") | F9: =COUNTIFS('Trang UXUI'!$B$5:$B$72,$A9,'Trang UXUI'!$M$5:$M$72,"☑") | G9: =COUNTIFS('Trang UXUI'!$B$5:$B$72,$A9,'Trang UXUI'!$N$5:$N$72,"✔ Xong") | H9: =IF(B9=0,0,G9/B9)
A10: G. Thuê / mượn | B10: =COUNTIF('Trang UXUI'!$B$5:$B$72,A10) | C10: =COUNTIFS('Trang UXUI'!$B$5:$B$72,$A10,'Trang UXUI'!$J$5:$J$72,"☑") | D10: =COUNTIFS('Trang UXUI'!$B$5:$B$72,$A10,'Trang UXUI'!$K$5:$K$72,"☑") | E10: =COUNTIFS('Trang UXUI'!$B$5:$B$72,$A10,'Trang UXUI'!$L$5:$L$72,"☑") | F10: =COUNTIFS('Trang UXUI'!$B$5:$B$72,$A10,'Trang UXUI'!$M$5:$M$72,"☑") | G10: =COUNTIFS('Trang UXUI'!$B$5:$B$72,$A10,'Trang UXUI'!$N$5:$N$72,"✔ Xong") | H10: =IF(B10=0,0,G10/B10)
A11: H. Kiểm kê & điều chỉnh | B11: =COUNTIF('Trang UXUI'!$B$5:$B$72,A11) | C11: =COUNTIFS('Trang UXUI'!$B$5:$B$72,$A11,'Trang UXUI'!$J$5:$J$72,"☑") | D11: =COUNTIFS('Trang UXUI'!$B$5:$B$72,$A11,'Trang UXUI'!$K$5:$K$72,"☑") | E11: =COUNTIFS('Trang UXUI'!$B$5:$B$72,$A11,'Trang UXUI'!$L$5:$L$72,"☑") | F11: =COUNTIFS('Trang UXUI'!$B$5:$B$72,$A11,'Trang UXUI'!$M$5:$M$72,"☑") | G11: =COUNTIFS('Trang UXUI'!$B$5:$B$72,$A11,'Trang UXUI'!$N$5:$N$72,"✔ Xong") | H11: =IF(B11=0,0,G11/B11)
A12: I. Chuyển kho | B12: =COUNTIF('Trang UXUI'!$B$5:$B$72,A12) | C12: =COUNTIFS('Trang UXUI'!$B$5:$B$72,$A12,'Trang UXUI'!$J$5:$J$72,"☑") | D12: =COUNTIFS('Trang UXUI'!$B$5:$B$72,$A12,'Trang UXUI'!$K$5:$K$72,"☑") | E12: =COUNTIFS('Trang UXUI'!$B$5:$B$72,$A12,'Trang UXUI'!$L$5:$L$72,"☑") | F12: =COUNTIFS('Trang UXUI'!$B$5:$B$72,$A12,'Trang UXUI'!$M$5:$M$72,"☑") | G12: =COUNTIFS('Trang UXUI'!$B$5:$B$72,$A12,'Trang UXUI'!$N$5:$N$72,"✔ Xong") | H12: =IF(B12=0,0,G12/B12)
A13: J. Báo cáo | B13: =COUNTIF('Trang UXUI'!$B$5:$B$72,A13) | C13: =COUNTIFS('Trang UXUI'!$B$5:$B$72,$A13,'Trang UXUI'!$J$5:$J$72,"☑") | D13: =COUNTIFS('Trang UXUI'!$B$5:$B$72,$A13,'Trang UXUI'!$K$5:$K$72,"☑") | E13: =COUNTIFS('Trang UXUI'!$B$5:$B$72,$A13,'Trang UXUI'!$L$5:$L$72,"☑") | F13: =COUNTIFS('Trang UXUI'!$B$5:$B$72,$A13,'Trang UXUI'!$M$5:$M$72,"☑") | G13: =COUNTIFS('Trang UXUI'!$B$5:$B$72,$A13,'Trang UXUI'!$N$5:$N$72,"✔ Xong") | H13: =IF(B13=0,0,G13/B13)
A14: K. Quản trị | B14: =COUNTIF('Trang UXUI'!$B$5:$B$72,A14) | C14: =COUNTIFS('Trang UXUI'!$B$5:$B$72,$A14,'Trang UXUI'!$J$5:$J$72,"☑") | D14: =COUNTIFS('Trang UXUI'!$B$5:$B$72,$A14,'Trang UXUI'!$K$5:$K$72,"☑") | E14: =COUNTIFS('Trang UXUI'!$B$5:$B$72,$A14,'Trang UXUI'!$L$5:$L$72,"☑") | F14: =COUNTIFS('Trang UXUI'!$B$5:$B$72,$A14,'Trang UXUI'!$M$5:$M$72,"☑") | G14: =COUNTIFS('Trang UXUI'!$B$5:$B$72,$A14,'Trang UXUI'!$N$5:$N$72,"✔ Xong") | H14: =IF(B14=0,0,G14/B14)
A15: L. Trả hàng bán (P2) | B15: =COUNTIF('Trang UXUI'!$B$5:$B$72,A15) | C15: =COUNTIFS('Trang UXUI'!$B$5:$B$72,$A15,'Trang UXUI'!$J$5:$J$72,"☑") | D15: =COUNTIFS('Trang UXUI'!$B$5:$B$72,$A15,'Trang UXUI'!$K$5:$K$72,"☑") | E15: =COUNTIFS('Trang UXUI'!$B$5:$B$72,$A15,'Trang UXUI'!$L$5:$L$72,"☑") | F15: =COUNTIFS('Trang UXUI'!$B$5:$B$72,$A15,'Trang UXUI'!$M$5:$M$72,"☑") | G15: =COUNTIFS('Trang UXUI'!$B$5:$B$72,$A15,'Trang UXUI'!$N$5:$N$72,"✔ Xong") | H15: =IF(B15=0,0,G15/B15)
A16: TỔNG | B16: =SUM(B4:B15) | C16: =SUM(C4:C15) | D16: =SUM(D4:D15) | E16: =SUM(E4:E15) | F16: =SUM(F4:F15) | G16: =SUM(G4:G15) | H16: =IF(B16=0,0,G16/B16)
A19: Theo milestone | B19: Số màn hình | C19: Hoàn thành | D19: % hoàn thành | E19: Mốc
A20: M1 | B20: =COUNTIF('Trang UXUI'!$I$5:$I$72,A20) | C20: =COUNTIFS('Trang UXUI'!$I$5:$I$72,A20,'Trang UXUI'!$N$5:$N$72,"✔ Xong") | D20: =IF(B20=0,0,C20/B20) | E20: Tuần 1–5: nền tảng & xác thực
A21: M2 | B21: =COUNTIF('Trang UXUI'!$I$5:$I$72,A21) | C21: =COUNTIFS('Trang UXUI'!$I$5:$I$72,A21,'Trang UXUI'!$N$5:$N$72,"✔ Xong") | D21: =IF(B21=0,0,C21/B21) | E21: Tuần 6–8: danh mục & quản trị
A22: M3 | B22: =COUNTIF('Trang UXUI'!$I$5:$I$72,A22) | C22: =COUNTIFS('Trang UXUI'!$I$5:$I$72,A22,'Trang UXUI'!$N$5:$N$72,"✔ Xong") | D22: =IF(B22=0,0,C22/B22) | E22: Tuần 8–10: nhập & xuất kho
A23: M4 | B23: =COUNTIF('Trang UXUI'!$I$5:$I$72,A23) | C23: =COUNTIFS('Trang UXUI'!$I$5:$I$72,A23,'Trang UXUI'!$N$5:$N$72,"✔ Xong") | D23: =IF(B23=0,0,C23/B23) | E23: Tuần 10–12: thuê, kiểm kê
A24: M5 | B24: =COUNTIF('Trang UXUI'!$I$5:$I$72,A24) | C24: =COUNTIFS('Trang UXUI'!$I$5:$I$72,A24,'Trang UXUI'!$N$5:$N$72,"✔ Xong") | D24: =IF(B24=0,0,C24/B24) | E24: Tuần 11–13: dashboard, báo cáo
A25: M6 | B25: =COUNTIF('Trang UXUI'!$I$5:$I$72,A25) | C25: =COUNTIFS('Trang UXUI'!$I$5:$I$72,A25,'Trang UXUI'!$N$5:$N$72,"✔ Xong") | D25: =IF(B25=0,0,C25/B25) | E25: Phase 2 (sau 27/12/2026)
A26: Chờ chốt | B26: =COUNTIF('Trang UXUI'!$I$5:$I$72,A26) | C26: =COUNTIFS('Trang UXUI'!$I$5:$I$72,A26,'Trang UXUI'!$N$5:$N$72,"✔ Xong") | D26: =IF(B26=0,0,C26/B26) | E26: Cần chốt G-1 / phạm vi v6

Sheet Trang UXUI
A1: TIGERNET — CHECKLIST CÁC TRANG UX/UI CẦN THỰC HIỆN
A2: Hướng dẫn: chỉ sửa 4 cột checkbox màu vàng (Thiết kế → Code UI → Nối API → Test) bằng cách chọn ☐/☑ ở dropdown. Cột 'Hoàn thành' tự tính; dòng đủ 4 ô ☑ tự chuyển xanh. Nguồn: BACKLOG.md, NOTE UXUI (Kế hoạch TigerNet.xlsx), BIEU_MAU.md, Backend_Structure_v6.md.
A4: STT | B4: Nhóm | C4: Trang / Màn hình | D4: Route (go_router) | E4: Story | F4: NOTE UXUI | G4: Vai trò | H4: Ưu tiên | I4: Milestone | J4: Thiết kế | K4: Code UI | L4: Nối API | M4: Test (responsive + dark) | N4: Hoàn thành | O4: Ngày xong | P4: Ghi chú
A5: 1 | B5: A. Công khai & xác thực | C5: Trang chủ công khai | D5: / | E5: PUB-01 | F5: #12 | G5: Khách | H5: P1 | I5: M1 | J5: ☐ | K5: ☐ | L5: ☐ | M5: ☐ | N5: =IF(COUNTIF(J5:M5,"☑")=4,"✔ Xong",COUNTIF(J5:M5,"☑")&"/4") | P5: Chưa đăng nhập chỉ thấy trang này
A6: 2 | B6: A. Công khai & xác thực | C6: Đăng nhập | D6: /login | E6: PUB-02 | F6: #11 | G6: Tất cả | H6: P1 | I6: M1 | J6: ☐ | K6: ☐ | L6: ☐ | M6: ☐ | N6: =IF(COUNTIF(J6:M6,"☑")=4,"✔ Xong",COUNTIF(J6:M6,"☑")&"/4") | P6: Báo khoá 15' sau 5 lần sai
A7: 3 | B7: A. Công khai & xác thực | C7: Quên mật khẩu - nhập email | D7: /forgot-password | E7: PUB-03 | F7: #11 | G7: Tất cả | H7: P1 | I7: M2 | J7: ☐ | K7: ☐ | L7: ☐ | M7: ☐ | N7: =IF(COUNTIF(J7:M7,"☑")=4,"✔ Xong",COUNTIF(J7:M7,"☑")&"/4") | P7: Không tiết lộ email có tồn tại
A8: 4 | B8: A. Công khai & xác thực | C8: Quên mật khẩu - nhập OTP | D8: /forgot-password/otp | E8: PUB-03 | F8: #11 | G8: Tất cả | H8: P1 | I8: M2 | J8: ☐ | K8: ☐ | L8: ☐ | M8: ☐ | N8: =IF(COUNTIF(J8:M8,"☑")=4,"✔ Xong",COUNTIF(J8:M8,"☑")&"/4") | P8: OTP hiệu lực 10 phút
A9: 5 | B9: A. Công khai & xác thực | C9: Đặt lại mật khẩu | D9: /reset-password | E9: PUB-03 | F9: #11 | G9: Tất cả | H9: P1 | I9: M2 | J9: ☐ | K9: ☐ | L9: ☐ | M9: ☐ | N9: =IF(COUNTIF(J9:M9,"☑")=4,"✔ Xong",COUNTIF(J9:M9,"☑")&"/4")
A10: 6 | B10: A. Công khai & xác thực | C10: Đăng ký | D10: /register | E10: PUB-04 | F10: #11 | G10: Khách | H10: Chờ chốt | I10: Chờ chốt | J10: ☐ | K10: ☐ | L10: ☐ | M10: ☐ | N10: =IF(COUNTIF(J10:M10,"☑")=4,"✔ Xong",COUNTIF(J10:M10,"☑")&"/4") | P10: G-1: chưa có API, khuyến nghị bỏ
A11: 7 | B11: B. Khung ứng dụng | C11: AppShell: Navbar + menu theo vai trò + bộ chọn kho + chuông + nút sáng/tối | D11: (shell /app/**) | E11: PUB-01, CHUNG-01, CHUNG-07 | F11: #7, #12 | G11: Tất cả | H11: P1 | I11: M1 | J11: ☐ | K11: ☐ | L11: ☐ | M11: ☐ | N11: =IF(COUNTIF(J11:M11,"☑")=4,"✔ Xong",COUNTIF(J11:M11,"☑")&"/4") | P11: Logo to, chữ navbar size 20
A12: 8 | B12: B. Khung ứng dụng | C12: Pop-up cảnh báo khi vào trang | D12: (dialog) | E12: CHUNG-04 | F12: #8 | G12: Tất cả | H12: P1 | I12: M5 | J12: ☐ | K12: ☐ | L12: ☐ | M12: ☐ | N12: =IF(COUNTIF(J12:M12,"☑")=4,"✔ Xong",COUNTIF(J12:M12,"☑")&"/4") | P12: Badge số chưa đọc phải nổi bật
A13: 9 | B13: B. Khung ứng dụng | C13: Trung tâm cảnh báo | D13: /app/alerts | E13: CHUNG-04 | F13: #8 | G13: Tất cả | H13: P1 | I13: M5 | J13: ☐ | K13: ☐ | L13: ☐ | M13: ☐ | N13: =IF(COUNTIF(J13:M13,"☑")=4,"✔ Xong",COUNTIF(J13:M13,"☑")&"/4") | P13: 4 loại: LOW_STOCK, RENTAL_EXPIRING, RENTAL_OVERDUE, PENDING_APPROVAL
A14: 10 | B14: B. Khung ứng dụng | C14: Hồ sơ cá nhân | D14: /app/profile | E14: CHUNG-01 | G14: Tất cả | H14: P1 | I14: M1 | J14: ☐ | K14: ☐ | L14: ☐ | M14: ☐ | N14: =IF(COUNTIF(J14:M14,"☑")=4,"✔ Xong",COUNTIF(J14:M14,"☑")&"/4")
A15: 11 | B15: B. Khung ứng dụng | C15: Đổi mật khẩu | D15: /app/profile/password | E15: CHUNG-02 | G15: Tất cả | H15: P1 | I15: M1 | J15: ☐ | K15: ☐ | L15: ☐ | M15: ☐ | N15: =IF(COUNTIF(J15:M15,"☑")=4,"✔ Xong",COUNTIF(J15:M15,"☑")&"/4")
A16: 12 | B16: B. Khung ứng dụng | C16: Dashboard | D16: /app/dashboard | E16: CHUNG-03 | F16: #5 | G16: Tất cả | H16: P1 | I16: M5 | J16: ☐ | K16: ☐ | L16: ☐ | M16: ☐ | N16: =IF(COUNTIF(J16:M16,"☑")=4,"✔ Xong",COUNTIF(J16:M16,"☑")&"/4") | P16: Biểu đồ nhập/xuất đặt đầu trang
A17: 13 | B17: B. Khung ứng dụng | C17: Trang lỗi 403 / 404 | D17: /403, /404 | E17: PUB-01 | G17: Tất cả | H17: P1 | I17: M1 | J17: ☐ | K17: ☐ | L17: ☐ | M17: ☐ | N17: =IF(COUNTIF(J17:M17,"☑")=4,"✔ Xong",COUNTIF(J17:M17,"☑")&"/4")
A18: 14 | B18: C. Danh mục | C18: Sản phẩm - danh sách | D18: /app/products | E18: TK-01 | F18: #1, #13 | G18: TK, QL (KT, BH xem) | H18: P1 | I18: M2 | J18: ☐ | K18: ☐ | L18: ☐ | M18: ☐ | N18: =IF(COUNTIF(J18:M18,"☑")=4,"✔ Xong",COUNTIF(J18:M18,"☑")&"/4")
A19: 15 | B19: C. Danh mục | C19: Sản phẩm - form thêm/sửa | D19: /app/products/new, /:id/edit | E19: TK-01 | G19: TK, QL | H19: P1 | I19: M2 | J19: ☐ | K19: ☐ | L19: ☐ | M19: ☐ | N19: =IF(COUNTIF(J19:M19,"☑")=4,"✔ Xong",COUNTIF(J19:M19,"☑")&"/4") | P19: Cờ is_serializable, min_stock_level
A20: 16 | B20: C. Danh mục | C20: Sản phẩm - chi tiết (tab serial) | D20: /app/products/:id | E20: TK-01 | G20: TK, QL | H20: P1 | I20: M2 | J20: ☐ | K20: ☐ | L20: ☐ | M20: ☐ | N20: =IF(COUNTIF(J20:M20,"☑")=4,"✔ Xong",COUNTIF(J20:M20,"☑")&"/4") | P20: Ảnh SP là P2 (TK-04)
A21: 17 | B21: C. Danh mục | C21: Nhóm sản phẩm | D21: /app/product-groups | E21: QL-06 | G21: QL | H21: P1 | I21: M2 | J21: ☐ | K21: ☐ | L21: ☐ | M21: ☐ | N21: =IF(COUNTIF(J21:M21,"☑")=4,"✔ Xong",COUNTIF(J21:M21,"☑")&"/4") | P21: Nhóm còn SP không xoá được (409)
A22: 18 | B22: C. Danh mục | C22: Nhà cung cấp - danh sách | D22: /app/suppliers | E22: TK-03 | F22: #1, #13 | G22: TK, QL (KT xem) | H22: P1 | I22: M2 | J22: ☐ | K22: ☐ | L22: ☐ | M22: ☐ | N22: =IF(COUNTIF(J22:M22,"☑")=4,"✔ Xong",COUNTIF(J22:M22,"☑")&"/4")
A23: 19 | B23: C. Danh mục | C23: Nhà cung cấp - form thêm/sửa | D23: /app/suppliers/new, /:id/edit | E23: TK-03 | G23: TK, QL | H23: P1 | I23: M2 | J23: ☐ | K23: ☐ | L23: ☐ | M23: ☐ | N23: =IF(COUNTIF(J23:M23,"☑")=4,"✔ Xong",COUNTIF(J23:M23,"☑")&"/4")
A24: 20 | B24: C. Danh mục | C24: Nhà cung cấp - chi tiết (lịch sử nhập) | D24: /app/suppliers/:id | E24: TK-03 | G24: TK, KT, QL | H24: P1 | I24: M2 | J24: ☐ | K24: ☐ | L24: ☐ | M24: ☐ | N24: =IF(COUNTIF(J24:M24,"☑")=4,"✔ Xong",COUNTIF(J24:M24,"☑")&"/4")
A25: 21 | B25: C. Danh mục | C25: NCC - tab tài liệu đính kèm | D25: /app/suppliers/:id | E25: TK-04 | G25: TK, QL | H25: P2 | I25: M6 | J25: ☐ | K25: ☐ | L25: ☐ | M25: ☐ | N25: =IF(COUNTIF(J25:M25,"☑")=4,"✔ Xong",COUNTIF(J25:M25,"☑")&"/4")
A26: 22 | B26: C. Danh mục | C26: NCC - tab tài khoản ngân hàng | D26: /app/suppliers/:id | E26: KT-08 | G26: KT, QL | H26: P2 | I26: M6 | J26: ☐ | K26: ☐ | L26: ☐ | M26: ☐ | N26: =IF(COUNTIF(J26:M26,"☑")=4,"✔ Xong",COUNTIF(J26:M26,"☑")&"/4")
A27: 23 | B27: C. Danh mục | C27: Khách hàng - danh sách | D27: /app/customers | E27: BH-01 | F27: #1, #13 | G27: BH, QL | H27: P1 | I27: M2 | J27: ☐ | K27: ☐ | L27: ☐ | M27: ☐ | N27: =IF(COUNTIF(J27:M27,"☑")=4,"✔ Xong",COUNTIF(J27:M27,"☑")&"/4")
A28: 24 | B28: C. Danh mục | C28: Khách hàng - form thêm/sửa | D28: /app/customers/new, /:id/edit | E28: BH-01 | G28: BH, QL | H28: P1 | I28: M2 | J28: ☐ | K28: ☐ | L28: ☐ | M28: ☐ | N28: =IF(COUNTIF(J28:M28,"☑")=4,"✔ Xong",COUNTIF(J28:M28,"☑")&"/4") | P28: Phân biệt KH bán / KH thuê
A29: 25 | B29: C. Danh mục | C29: Khách hàng - chi tiết + người nhận (dialog) | D29: /app/customers/:id | E29: BH-02 | G29: BH, QL | H29: P1 | I29: M2 | J29: ☐ | K29: ☐ | L29: ☐ | M29: ☐ | N29: =IF(COUNTIF(J29:M29,"☑")=4,"✔ Xong",COUNTIF(J29:M29,"☑")&"/4") | P29: 1 KH nhiều người nhận, 1 mặc định
A30: 26 | B30: C. Danh mục | C30: Kho hàng + phân công nhân viên | D30: /app/warehouses | E30: QL-12, QT-07, CHUNG-07 | G30: QL, QT | H30: P1 | I30: M2 | J30: ☐ | K30: ☐ | L30: ☐ | M30: ☐ | N30: =IF(COUNTIF(J30:M30,"☑")=4,"✔ Xong",COUNTIF(J30:M30,"☑")&"/4") | P30: ERD v6 — phân công kho cho user (QT-07) mở từ form người dùng
A31: 27 | B31: D. Tồn kho | C31: Tồn kho - danh sách & lọc | D31: /app/inventory | E31: TK-02, KT-02 | F31: #1, #13 | G31: TK, KT, QL | H31: P1 | I31: M2 | J31: ☐ | K31: ☐ | L31: ☐ | M31: ☐ | N31: =IF(COUNTIF(J31:M31,"☑")=4,"✔ Xong",COUNTIF(J31:M31,"☑")&"/4") | P31: Lọc SP/serial/trạng thái/ngày
A32: 28 | B32: D. Tồn kho | C32: Tổng hợp tồn theo kho | D32: /app/inventory/summary | E32: TK-02 | G32: TK, KT, QL | H32: P1 | I32: M2 | J32: ☐ | K32: ☐ | L32: ☐ | M32: ☐ | N32: =IF(COUNTIF(J32:M32,"☑")=4,"✔ Xong",COUNTIF(J32:M32,"☑")&"/4")
A33: 29 | B33: D. Tồn kho | C33: Hàng dưới ngưỡng | D33: /app/inventory/low-stock | E33: TK-02 | G33: TK, QL | H33: P1 | I33: M2 | J33: ☐ | K33: ☐ | L33: ☐ | M33: ☐ | N33: =IF(COUNTIF(J33:M33,"☑")=4,"✔ Xong",COUNTIF(J33:M33,"☑")&"/4") | P33: Dòng đánh dấu đỏ
A34: 30 | B34: E. Phiếu nhập | C34: Phiếu nhập - danh sách | D34: /app/import-receipts | E34: KT-01 | F34: #1, #13 | G34: TK, KT, QL | H34: P1 | I34: M3 | J34: ☐ | K34: ☐ | L34: ☐ | M34: ☐ | N34: =IF(COUNTIF(J34:M34,"☑")=4,"✔ Xong",COUNTIF(J34:M34,"☑")&"/4") | P34: Lọc NCC, ngày, trạng thái
A35: 31 | B35: E. Phiếu nhập | C35: Phiếu nhập - form tạo/sửa | D35: /app/import-receipts/new, /:id/edit | E35: TK-05, TK-06 | G35: TK | H35: P1 | I35: M3 | J35: ☐ | K35: ☐ | L35: ☐ | M35: ☐ | N35: =IF(COUNTIF(J35:M35,"☑")=4,"✔ Xong",COUNTIF(J35:M35,"☑")&"/4") | P35: Nhiều dòng SP + serial, tự tính tổng
A36: 32 | B36: E. Phiếu nhập | C36: Phiếu nhập - chi tiết (xác nhận / huỷ / in) | D36: /app/import-receipts/:id | E36: TK-07, TK-08, TK-09, QL-02 | G36: TK, KT, QL | H36: P1 | I36: M3 | J36: ☐ | K36: ☐ | L36: ☐ | M36: ☐ | N36: =IF(COUNTIF(J36:M36,"☑")=4,"✔ Xong",COUNTIF(J36:M36,"☑")&"/4") | P36: In mẫu 1 (01-VT)
A37: 33 | B37: F. Phiếu xuất | C37: Phiếu xuất - danh sách | D37: /app/export-receipts | E37: BH-06 | F37: #1, #13 | G37: BH, TK, KT, QL | H37: P1 | I37: M3 | J37: ☐ | K37: ☐ | L37: ☐ | M37: ☐ | N37: =IF(COUNTIF(J37:M37,"☑")=4,"✔ Xong",COUNTIF(J37:M37,"☑")&"/4") | P37: Lọc trạng thái/KH/ngày
A38: 34 | B38: F. Phiếu xuất | C38: Phiếu xuất - form tạo/sửa | D38: /app/export-receipts/new, /:id/edit | E38: BH-03, BH-04, TK-10 | G38: BH | H38: P1 | I38: M3 | J38: ☐ | K38: ☐ | L38: ☐ | M38: ☐ | N38: =IF(COUNTIF(J38:M38,"☑")=4,"✔ Xong",COUNTIF(J38:M38,"☑")&"/4") | P38: Kiểm tra tồn realtime, chọn VAT
A39: 35 | B39: F. Phiếu xuất | C39: Phiếu xuất - chi tiết (duyệt / hoàn tất xuất) | D39: /app/export-receipts/:id | E39: QL-01, TK-11 | G39: BH, TK, KT, QL | H39: P1 | I39: M3 | J39: ☐ | K39: ☐ | L39: ☐ | M39: ☐ | N39: =IF(COUNTIF(J39:M39,"☑")=4,"✔ Xong",COUNTIF(J39:M39,"☑")&"/4") | P39: PENDING → CONFIRMED → EXPORTED
A40: 36 | B40: F. Phiếu xuất | C40: Dialog ghi nhận thanh toán | D40: (dialog) | E40: KT-03 | G40: KT | H40: P1 | I40: M3 | J40: ☐ | K40: ☐ | L40: ☐ | M40: ☐ | N40: =IF(COUNTIF(J40:M40,"☑")=4,"✔ Xong",COUNTIF(J40:M40,"☑")&"/4") | P40: Không vượt số còn lại; huỷ thay vì sửa
A41: 37 | B41: F. Phiếu xuất | C41: In phiếu xuất / phiếu giao hàng | D41: (menu in) | E41: KT-04, BH-05, BH-13 | G41: BH, TK, KT | H41: P1 | I41: M3 | J41: ☐ | K41: ☐ | L41: ☐ | M41: ☐ | N41: =IF(COUNTIF(J41:M41,"☑")=4,"✔ Xong",COUNTIF(J41:M41,"☑")&"/4") | P41: Mẫu 2 (02-VT), mẫu 3 (A5, không giá)
A42: 38 | B42: G. Thuê / mượn | C42: Phiếu thuê/mượn - danh sách (tab RENT / LEND) | D42: /app/rentals | E42: BH-09 | F42: #1, #13 | G42: BH, TK, QL | H42: P1 | I42: M4 | J42: ☐ | K42: ☐ | L42: ☐ | M42: ☐ | N42: =IF(COUNTIF(J42:M42,"☑")=4,"✔ Xong",COUNTIF(J42:M42,"☑")&"/4")
A43: 39 | B43: G. Thuê / mượn | C43: Phiếu thuê/mượn - form tạo/sửa | D43: /app/rentals/new, /:id/edit | E43: BH-07, BH-08 | G43: BH | H43: P1 | I43: M4 | J43: ☐ | K43: ☐ | L43: ☐ | M43: ☐ | N43: =IF(COUNTIF(J43:M43,"☑")=4,"✔ Xong",COUNTIF(J43:M43,"☑")&"/4") | P43: LEND: không cọc, giá/ngày chỉ để tính phạt
A44: 40 | B44: G. Thuê / mượn | C44: Phiếu thuê/mượn - chi tiết + in | D44: /app/rentals/:id | E44: BH-09, TK-16 | G44: BH, TK, QL | H44: P1 | I44: M4 | J44: ☐ | K44: ☐ | L44: ☐ | M44: ☐ | N44: =IF(COUNTIF(J44:M44,"☑")=4,"✔ Xong",COUNTIF(J44:M44,"☑")&"/4") | P44: In mẫu 4
A45: 41 | B45: G. Thuê / mượn | C45: Danh sách sắp hết hạn (7 ngày) | D45: /app/rentals/expiring | E45: BH-09 | G45: BH, QL | H45: P1 | I45: M4 | J45: ☐ | K45: ☐ | L45: ☐ | M45: ☐ | N45: =IF(COUNTIF(J45:M45,"☑")=4,"✔ Xong",COUNTIF(J45:M45,"☑")&"/4")
A46: 42 | B46: G. Thuê / mượn | C46: Trả hàng thuê/mượn (tình trạng serial, phạt, hoàn cọc) | D46: /app/rentals/:id/return | E46: TK-12, BH-10 | G46: TK, BH | H46: P1 | I46: M4 | J46: ☐ | K46: ☐ | L46: ☐ | M46: ☐ | N46: =IF(COUNTIF(J46:M46,"☑")=4,"✔ Xong",COUNTIF(J46:M46,"☑")&"/4") | P46: Phạt khi quá hạn ≥10 ngày
A47: 43 | B47: G. Thuê / mượn | C47: Phiếu trả - danh sách & chi tiết + in | D47: /app/rental-returns | E47: TK-12, TK-16 | G47: TK, BH, QL | H47: P1 | I47: M4 | J47: ☐ | K47: ☐ | L47: ☐ | M47: ☐ | N47: =IF(COUNTIF(J47:M47,"☑")=4,"✔ Xong",COUNTIF(J47:M47,"☑")&"/4") | P47: In mẫu 5
A48: 44 | B48: H. Kiểm kê & điều chỉnh | C48: Kiểm kê - danh sách | D48: /app/stocktakes | E48: TK-13 | F48: #1, #13 | G48: TK, QL | H48: P1 | I48: M4 | J48: ☐ | K48: ☐ | L48: ☐ | M48: ☐ | N48: =IF(COUNTIF(J48:M48,"☑")=4,"✔ Xong",COUNTIF(J48:M48,"☑")&"/4")
A49: 45 | B49: H. Kiểm kê & điều chỉnh | C49: Kiểm kê - tạo phiếu | D49: /app/stocktakes/new | E49: TK-13 | G49: TK | H49: P1 | I49: M4 | J49: ☐ | K49: ☐ | L49: ☐ | M49: ☐ | N49: =IF(COUNTIF(J49:M49,"☑")=4,"✔ Xong",COUNTIF(J49:M49,"☑")&"/4")
A50: 46 | B50: H. Kiểm kê & điều chỉnh | C50: Kiểm kê - nhập số liệu thực tế | D50: /app/stocktakes/:id/count | E50: TK-13 | G50: TK | H50: P1 | I50: M4 | J50: ☐ | K50: ☐ | L50: ☐ | M50: ☐ | N50: =IF(COUNTIF(J50:M50,"☑")=4,"✔ Xong",COUNTIF(J50:M50,"☑")&"/4") | P50: Tự tính chênh lệch, chặn số âm/bất thường
A51: 47 | B51: H. Kiểm kê & điều chỉnh | C51: Kiểm kê - chi tiết + chốt + in | D51: /app/stocktakes/:id | E51: QL-03, TK-16 | G51: TK, QL | H51: P1 | I51: M4 | J51: ☐ | K51: ☐ | L51: ☐ | M51: ☐ | N51: =IF(COUNTIF(J51:M51,"☑")=4,"✔ Xong",COUNTIF(J51:M51,"☑")&"/4") | P51: In mẫu 6 (05-VT)
A52: 48 | B52: H. Kiểm kê & điều chỉnh | C52: Phiếu điều chỉnh - danh sách | D52: /app/adjustments | E52: KT-07 | F52: #1, #13 | G52: TK, KT, QL | H52: P1 | I52: M4 | J52: ☐ | K52: ☐ | L52: ☐ | M52: ☐ | N52: =IF(COUNTIF(J52:M52,"☑")=4,"✔ Xong",COUNTIF(J52:M52,"☑")&"/4")
A53: 49 | B53: H. Kiểm kê & điều chỉnh | C53: Kiểm kê đột xuất - chọn SP cần điều chỉnh | D53: /app/stocktakes/new?mode=adhoc | E53: TK-13 | G53: TK | H53: P1 | I53: M4 | J53: ☐ | K53: ☐ | L53: ☐ | M53: ☐ | N53: =IF(COUNTIF(J53:M53,"☑")=4,"✔ Xong",COUNTIF(J53:M53,"☑")&"/4") | P53: Thay form điều chỉnh thủ công (ERD v6, G-14); bắt buộc nhập lý do
A54: 50 | B54: H. Kiểm kê & điều chỉnh | C54: Phiếu điều chỉnh - chi tiết + in (chỉ xem) | D54: /app/adjustments/:id | E54: KT-07, TK-16 | G54: TK, KT, QL | H54: P1 | I54: M4 | J54: ☐ | K54: ☐ | L54: ☐ | M54: ☐ | N54: =IF(COUNTIF(J54:M54,"☑")=4,"✔ Xong",COUNTIF(J54:M54,"☑")&"/4") | P54: In mẫu 7; duyệt = chốt kiểm kê (QL-03)
A55: 51 | B55: I. Chuyển kho | C55: Chuyển kho - danh sách / form / chi tiết | D55: /app/transfers | E55: TK-17 | G55: TK, QL | H55: P2 | I55: M6 | J55: ☐ | K55: ☐ | L55: ☐ | M55: ☐ | N55: =IF(COUNTIF(J55:M55,"☑")=4,"✔ Xong",COUNTIF(J55:M55,"☑")&"/4") | P55: ERD v6 — chuyển kho để P2; in mẫu 11
A56: 52 | B56: J. Báo cáo | C56: Báo cáo tồn kho | D56: /app/reports/inventory | E56: TK-15 | G56: TK, KT, QL | H56: P1 | I56: M5 | J56: ☐ | K56: ☐ | L56: ☐ | M56: ☐ | N56: =IF(COUNTIF(J56:M56,"☑")=4,"✔ Xong",COUNTIF(J56:M56,"☑")&"/4") | P56: Xuất Excel/PDF
A57: 53 | B57: J. Báo cáo | C57: Báo cáo nhập-xuất (theo NCC/KH/SP) | D57: /app/reports/import-export | E57: KT-05, QL-10 | G57: KT, QL | H57: P1 | I57: M5 | J57: ☐ | K57: ☐ | L57: ☐ | M57: ☐ | N57: =IF(COUNTIF(J57:M57,"☑")=4,"✔ Xong",COUNTIF(J57:M57,"☑")&"/4") | P57: Xuất Excel/PDF
A58: 54 | B58: J. Báo cáo | C58: Báo cáo công nợ | D58: /app/reports/receivables | E58: KT-06, QL-10 | G58: KT, QL | H58: P1 | I58: M5 | J58: ☐ | K58: ☐ | L58: ☐ | M58: ☐ | N58: =IF(COUNTIF(J58:M58,"☑")=4,"✔ Xong",COUNTIF(J58:M58,"☑")&"/4") | P58: TK gọi phải 403
A59: 55 | B59: J. Báo cáo | C59: Biên bản đối chiếu công nợ | D59: /app/reports/reconciliation | E59: KT-09 | G59: KT, QL | H59: P1 | I59: M5 | J59: ☐ | K59: ☐ | L59: ☐ | M59: ☐ | N59: =IF(COUNTIF(J59:M59,"☑")=4,"✔ Xong",COUNTIF(J59:M59,"☑")&"/4") | P59: In mẫu 8 (chỉ phải thu, không số dư đầu kỳ — G-13)
A60: 56 | B60: J. Báo cáo | C60: In phiếu thu / phiếu chi | D60: (menu in) | E60: KT-10 | G60: KT | H60: P2 | I60: M6 | J60: ☐ | K60: ☐ | L60: ☐ | M60: ☐ | N60: =IF(COUNTIF(J60:M60,"☑")=4,"✔ Xong",COUNTIF(J60:M60,"☑")&"/4") | P60: In mẫu 9 (01-TT / 02-TT) — cần bảng thanh toán (G-13)
A61: 57 | B61: J. Báo cáo | C61: Báo cáo cho thuê / cho mượn | D61: /app/reports/rental | E61: QL-09 | G61: QL | H61: P1 | I61: M5 | J61: ☐ | K61: ☐ | L61: ☐ | M61: ☐ | N61: =IF(COUNTIF(J61:M61,"☑")=4,"✔ Xong",COUNTIF(J61:M61,"☑")&"/4") | P61: Tách riêng thuê và mượn
A62: 58 | B62: K. Quản trị | C62: Người dùng - danh sách | D62: /app/admin/users | E62: QL-08, QT-01 | F62: #1, #13 | G62: QT, QL (xem) | H62: P1 | I62: M2 | J62: ☐ | K62: ☐ | L62: ☐ | M62: ☐ | N62: =IF(COUNTIF(J62:M62,"☑")=4,"✔ Xong",COUNTIF(J62:M62,"☑")&"/4")
A63: 59 | B63: K. Quản trị | C63: Người dùng - form tạo/sửa/khoá | D63: /app/admin/users/new, /:id | E63: QT-01 | G63: QT | H63: P1 | I63: M2 | J63: ☐ | K63: ☐ | L63: ☐ | M63: ☐ | N63: =IF(COUNTIF(J63:M63,"☑")=4,"✔ Xong",COUNTIF(J63:M63,"☑")&"/4") | P63: Username chỉ đặt lúc tạo
A64: 60 | B64: K. Quản trị | C64: Vai trò & ma trận phân quyền | D64: /app/admin/roles | E64: QT-02 | G64: QT | H64: P1 | I64: M2 | J64: ☐ | K64: ☐ | L64: ☐ | M64: ☐ | N64: =IF(COUNTIF(J64:M64,"☑")=4,"✔ Xong",COUNTIF(J64:M64,"☑")&"/4") | P64: Chỉ xem
A65: 61 | B65: K. Quản trị | C65: Nhật ký hoạt động (audit log) | D65: /app/admin/audit-logs | E65: QT-03, QL-08 | F65: #1, #13 | G65: QT, QL | H65: P1 | I65: M2 | J65: ☐ | K65: ☐ | L65: ☐ | M65: ☐ | N65: =IF(COUNTIF(J65:M65,"☑")=4,"✔ Xong",COUNTIF(J65:M65,"☑")&"/4")
A66: 62 | B66: K. Quản trị | C66: Cấu hình mẫu VAT | D66: /app/admin/settings/vat | E66: QT-04 | G66: QT | H66: P1 | I66: M5 | J66: ☐ | K66: ☐ | L66: ☐ | M66: ☐ | N66: =IF(COUNTIF(J66:M66,"☑")=4,"✔ Xong",COUNTIF(J66:M66,"☑")&"/4") | P66: P1 chỉ xem; thêm/sửa là P2
A67: 63 | B67: K. Quản trị | C67: Cấu hình quy tắc thuê (7 / 10 ngày) | D67: /app/admin/settings/rental-rules | E67: QL-11 | G67: QL, QT | H67: P1 | I67: M4 | J67: ☐ | K67: ☐ | L67: ☐ | M67: ☐ | N67: =IF(COUNTIF(J67:M67,"☑")=4,"✔ Xong",COUNTIF(J67:M67,"☑")&"/4") | P67: P1 chỉ xem (G-2)
A68: 64 | B68: K. Quản trị | C68: Loại giao dịch & trạng thái thanh toán | D68: /app/admin/settings/lookups | E68: QT-05 | G68: QT | H68: P1 | I68: M5 | J68: ☐ | K68: ☐ | L68: ☐ | M68: ☐ | N68: =IF(COUNTIF(J68:M68,"☑")=4,"✔ Xong",COUNTIF(J68:M68,"☑")&"/4") | P68: Chỉ xem
A69: 65 | B69: K. Quản trị | C69: Thống kê truy cập theo tháng | D69: /app/admin/access-stats | E69: QT-06 | F69: #9 | G69: QT | H69: P2 | I69: M6 | J69: ☐ | K69: ☐ | L69: ☐ | M69: ☐ | N69: =IF(COUNTIF(J69:M69,"☑")=4,"✔ Xong",COUNTIF(J69:M69,"☑")&"/4") | P69: G-4
A70: 66 | B70: K. Quản trị | C70: Branding tenant (logo, màu) | D70: /app/admin/branding | E70: PUB-05 | G70: QT | H70: P2 | I70: M6 | J70: ☐ | K70: ☐ | L70: ☐ | M70: ☐ | N70: =IF(COUNTIF(J70:M70,"☑")=4,"✔ Xong",COUNTIF(J70:M70,"☑")&"/4")
A71: 67 | B71: L. Trả hàng bán (P2) | C71: Trả/đổi hàng bán - danh sách / form / chi tiết + duyệt | D71: /app/sales-returns | E71: BH-11, BH-12, QL-05 | G71: BH, QL | H71: P2 | I71: M6 | J71: ☐ | K71: ☐ | L71: ☐ | M71: ☐ | N71: =IF(COUNTIF(J71:M71,"☑")=4,"✔ Xong",COUNTIF(J71:M71,"☑")&"/4") | P71: In mẫu 10
A72: 68 | B72: L. Trả hàng bán (P2) | C72: Chính sách phí hoàn trả | D72: /app/sales-returns/fee-policies | E72: BH-11 | G72: QL | H72: P2 | I72: M6 | J72: ☐ | K72: ☐ | L72: ☐ | M72: ☐ | N72: =IF(COUNTIF(J72:M72,"☑")=4,"✔ Xong",COUNTIF(J72:M72,"☑")&"/4")

Sheet Quy định UI
A1: QUY ĐỊNH UI ÁP DỤNG TOÀN BỘ TRANG (NOTE UXUI + NFR-4)
A3: # | B3: Yêu cầu | C3: Trạng thái theo tài liệu | D3: Nơi xử lý trong frontend | E3: Đã code | F3: Ghi chú
A4: 1 | B4: Bảng dữ liệu: tăng cỡ chữ, kẻ dòng rõ, phân trang 20–50 dòng/trang | C4: Đã fix (thiết kế) | D4: shared/data_table/ | E4: ☐
A5: 2 | B5: Tiêu đề in hoa hết | C5: Đã fix (thiết kế) | D5: core/theme/app_typography.dart | E5: ☐
A6: 3 | B6: Thông tin quan trọng in đậm | C6: Đã fix (thiết kế) | D6: core/theme/app_typography.dart | E6: ☐
A7: 4 | B7: Tăng độ mờ của cửa sổ modal/dialog | C7: Đã fix (thiết kế) | D7: shared/feedback/app_modal.dart | E7: ☐
A8: 5 | B8: Dashboard: biểu đồ nhập/xuất lên đầu, co giãn theo màn hình | C8: Đã fix (thiết kế) | D8: features/dashboard/ | E8: ☐
A9: 6 | B9: Ảnh nền/minh hoạ sáng, sạch | C9: Đã fix (thiết kế) | D9: assets/ | E9: ☐
A10: 7 | B10: Navbar chữ size 20, logo to | C10: Đã fix (thiết kế) | D10: shared/layout/nav_bar.dart | E10: ☐
A11: 8 | B11: Cảnh báo pop-up mỗi lần vào trang + icon alert có số chưa đọc nổi bật | C11: Chưa fix | D11: features/alerts/ | E11: ☐
A12: 9 | B12: Trang admin: người dùng/vai trò, thống kê truy cập theo tháng | C12: Chưa fix (P2) | D12: features/admin/ | E12: ☐
A13: 10 | B13: Một font thống nhất (Geist), tiêu đề nổi bật dùng font khác | C13: Đã fix (thiết kế) | D13: core/theme/app_typography.dart | E13: ☐
A14: 11 | B14: Trang đăng nhập, đăng ký / quên mật khẩu (OTP email) | C14: Đã fix (thiết kế) - đăng ký chờ chốt G-1 | D14: features/auth/ | E14: ☐
A15: 12 | B15: Giới hạn menu & dữ liệu theo vai trò; khách chỉ xem trang công khai | C15: Chưa fix | D15: core/router/guards.dart, core/auth/permissions.dart | E15: ☐
... A19: 16 | B19: Dark / light mode | C19: NFR-4 | D19: core/theme/ | E19: ☐
